{
  "project_info": {
    "project_number": "173640462164",
    "project_id": "recon-mobile-42da3",
    "storage_bucket": "recon-mobile-42da3.firebasestorage.app"
  },
  "client": [
    {
      "client_info": {
        "mobilesdk_app_id": "1:173640462164:android:6f823d049934aac53522c1",
        "android_client_info": {
          "package_name": "com.reconmobile"
        }
      },
      "oauth_client": [],
      "api_key": [
        {
          "current_key": "AIzaSyBPo4_3Q3qhpsptWokAqyJJwS3iZJvF-WI"
        }
      ],
      "services": {
        "appinvite_service": {
          "other_platform_oauth_client": []
        }
      }
    }
  ],
  "configuration_version": "1"
}